{
    "领取绮思奖励": {
        "next": [
            "Click_活动"
        ],
        "interrupt": [
            "返回主界面"
        ]
    },
    "Click_活动": {
        "action": "Click",
        "recognition": "TemplateMatch",
        "template": "Button/活动.PNG",
        "pre_wait_freezes": 800,
        "post_delay": 1000,
        "roi": [
            28,
            454,
            42,
            41
        ],
        "next": [
            "Swipe_向左滑动寻找绮思"
        ]
    },
    "Swipe_向左滑动寻找绮思": {
        "action": "Swipe",
        "duration": 800,
        "post_wait_freezes": 400,
        "timeout": 10000,
        "begin": [
            640,
            1140,
            30,
            60
        ],
        "end": [
            45,
            1140,
            30,
            60
        ],
        "next": [
            "Flag_绮思",
            "Flag_每日签到"
        ],
        "interrupt": [
            "Swipe_向左滑动寻找绮思"
        ]
    },
    "Swipe_向右滑动寻找绮思": {
        "action": "Swipe",
        "duration": 800,
        "post_wait_freezes": 400,
        "timeout": 10000,
        "begin": [
            45,
            1140,
            30,
            60
        ],
        "end": [
            640,
            1140,
            30,
            60
        ],
        "next": [
            "Flag_绮思"
        ],
        "interrupt": [
            "Swipe_向右滑动寻找绮思"
        ]
    },
    "Flag_绮思": {
        "recognition": "OCR",
        "expected": "绮思",
        "post_delay": 3000,
        "roi": [
            18,
            1120,
            682,
            110
        ],
        "next": [
            "Click_绮思"
        ]
    },
    "Flag_每日签到": {
        "recognition": "OCR",
        "expected": [
            "每日",
            "签到"
        ],
        "post_delay": 1000,
        "roi": [
            18,
            1120,
            682,
            110
        ],
        "next": [
            "Swipe_向右滑动寻找绮思"
        ]
    },
    "Click_绮思": {
        "action": "Click",
        "recognition": "OCR",
        "expected": "绮思",
        "post_delay": 1500,
        "roi": [
            18,
            1120,
            682,
            110
        ],
        "next": [
            "Click_绮思任务"
        ],
        "interrupt": [
            "Click_X按钮"
        ]
    },
    "Click_绮思任务": {
        "action": "Click",
        "recognition": "OCR",
        "expected": "任务",
        "post_delay": 1000,
        "next": [
            "Flag_Inverse_绮思无领取键"
        ],
        "interrupt": [
            "Click_绮思等级提升",
            "Click_关闭绮思奖励弹窗",
            "Click_绮思领取"
        ]
    },
    "Flag_Inverse_绮思无领取键": {
        "inverse": true,
        "recognition": "OCR",
        "expected": "领取",
        "roi": [
            500,
            410,
            130,
            80
        ],
        "next": [
            "返回主界面"
        ]
    },
    "Click_绮思领取": {
        "action": "Click",
        "recognition": "OCR",
        "expected": "领取",
        "pre_delay": 800,
        "post_delay": 1000,
        "roi": [
            500,
            410,
            130,
            80
        ],
        "next": [
            "Click_绮思等级提升",
            "Click_关闭绮思奖励弹窗"
        ]
    },
    "Click_关闭绮思奖励弹窗": {
        "action": "Click",
        "recognition": "OCR",
        "expected": "获得奖励",
        "pre_delay": 1000,
        "post_delay": 1000,
        "target": [
            300,
            1000,
            30,
            30
        ],
        "roi": [
            305,
            230,
            110,
            200
        ],
        "next": [
            "Click_绮思等级提升",
            "Click_绮思任务"
        ]
    },
    "Click_绮思等级提升": {
        "action": "Click",
        "recognition": "OCR",
        "expected": [
            "绮思等级提升"
        ],
        "pre_delay": 800,
        "post_delay": 1000,
        "target": [
            300,
            900,
            30,
            30
        ],
        "roi": [
            276,
            389,
            163,
            41
        ],
        "next": [
            "Click_关闭绮思奖励弹窗",
            "Click_绮思任务"
        ]
    }
}